deposit_gui/LICENSE
deposit_gui/THIRDPARTY.TXT
deposit_gui/__init__.py
deposit_gui/_meta.py
deposit_gui/_version.py
deposit_gui/dgui_main.py
deposit_gui/controller/__init__.py
deposit_gui/controller/cactions.py
deposit_gui/controller/cdialogs.py
deposit_gui/controller/cmdiarea.py
deposit_gui/controller/cmodel.py
deposit_gui/controller/cnavigator.py
deposit_gui/controller/controller.py
deposit_gui/controller/cquerytoolbar.py
deposit_gui/controller/cusertools.py
deposit_gui/controller/cview.py
deposit_gui/dgui/__init__.py
deposit_gui/dgui/abstract_subcontroller.py
deposit_gui/dgui/abstract_subview.py
deposit_gui/dgui/dcactions.py
deposit_gui/dgui/dcdialogs.py
deposit_gui/dgui/dclickable_logo.py
deposit_gui/dgui/dcmodel.py
deposit_gui/dgui/dconnect_frame.py
deposit_gui/dgui/ddialog.py
deposit_gui/dgui/dgraph_view.py
deposit_gui/dgui/dgraphics_view.py
deposit_gui/dgui/dlogging.py
deposit_gui/dgui/dmain_window.py
deposit_gui/dgui/dmenu_bar.py
deposit_gui/dgui/dmodel.py
deposit_gui/dgui/dnotification.py
deposit_gui/dgui/dprogress.py
deposit_gui/dgui/dregistry.py
deposit_gui/dgui/dsave_as_postgres_frame.py
deposit_gui/dgui/dstatus_bar.py
deposit_gui/dgui/dtool_bar.py
deposit_gui/dgui/dvactions.py
deposit_gui/dgui/dvdialogs.py
deposit_gui/dgui/dview.py
deposit_gui/dgui/dconnect_tabs/__init__.py
deposit_gui/dgui/dconnect_tabs/abstract_tab_file.py
deposit_gui/dgui/dconnect_tabs/dconnect_tab_db.py
deposit_gui/dgui/dconnect_tabs/dconnect_tab_db_rel.py
deposit_gui/dgui/dconnect_tabs/dconnect_tab_json.py
deposit_gui/dgui/dconnect_tabs/dconnect_tab_memory.py
deposit_gui/dgui/dconnect_tabs/dconnect_tab_pickle.py
deposit_gui/dgui/dconnect_tabs/dconnect_tab_recent.py
deposit_gui/dgui/qss/__init__.py
deposit_gui/dgui/qss/dark.qss
deposit_gui/dialogs/__init__.py
deposit_gui/dialogs/dialog_about.py
deposit_gui/dialogs/dialog_add_relation.py
deposit_gui/dialogs/dialog_connect.py
deposit_gui/dialogs/dialog_import_external.py
deposit_gui/dialogs/dialog_import_source.py
deposit_gui-1.6.36.dist-info/LICENSE
deposit_gui-1.6.36.dist-info/METADATA
deposit_gui-1.6.36.dist-info/WHEEL
deposit_gui-1.6.36.dist-info/top_level.txt
deposit_gui-1.6.36.dist-info/RECORD
