Metadata-Version: 2.1
Name: deposit_gui
Version: 1.6.36
Summary: GUI for Deposit - Graph database for scientific data collection
Author-email: Peter Demján <peter.demjan@gmail.com>
License: GNU General Public License v3 (GPLv3)
Project-URL: homepage, https://github.com/demjanp/deposit_gui
Keywords: database,graph
Classifier: Development Status :: 5 - Production/Stable
Classifier: Intended Audience :: Science/Research
Classifier: Topic :: Database
Classifier: License :: OSI Approved :: GNU General Public License v3 (GPLv3)
Classifier: Programming Language :: Python :: 3.10
Classifier: Operating System :: Microsoft :: Windows :: Windows 10
Requires-Python: <4,>=3.10
License-File: LICENSE
Requires-Dist: deposit<2,>=1.6.36
Requires-Dist: PySide6<7,>=6.7.2
Requires-Dist: svgelements<2,>=1.9.6
Requires-Dist: pyobjc<11,>=10.3.1; sys_platform == "darwin"
Requires-Dist: pexpect<5,>=4.9.0; sys_platform == "darwin"
Requires-Dist: pygraphviz<2,>=1.13; sys_platform == "linux" or sys_platform == "linux2"
Requires-Dist: tqdm<5,>=4.66.4; sys_platform == "win32"
Requires-Dist: requests<3,>=2.32.3; sys_platform == "win32"
